statemachines_orchestrator/__init__.py
statemachines_orchestrator/exceptions.py
statemachines_orchestrator/orchestrator.py
statemachines_orchestrator/utils.py
statemachines_orchestrator-0.0.4.dist-info/licenses/LICENSE
statemachines_orchestrator-0.0.4.dist-info/METADATA
statemachines_orchestrator-0.0.4.dist-info/WHEEL
statemachines_orchestrator-0.0.4.dist-info/top_level.txt
statemachines_orchestrator-0.0.4.dist-info/RECORD
