Metadata-Version: 2.4
Name: statemachines_orchestrator
Version: 0.0.4
Summary: An extension of `python-statemachine` with linking between machines.
Project-URL: Homepage, https://github.com/Neikow/statemachines_orchestrator
Project-URL: Issues, https://github.com/Neikow/statemachines_orchestrator/issues
Keywords: statemachine,orchestrator,state machine,python-statemachine
Classifier: Programming Language :: Python :: 3
Classifier: Operating System :: OS Independent
Requires-Python: >=3.11
License-File: LICENSE
Requires-Dist: python-statemachine==2.5.0
Dynamic: license-file
